flottekarte/__init__.py
flottekarte/axes.py
flottekarte/extent.py
flottekarte/grid.py
flottekarte/interpolate.py
flottekarte/map.py
flottekarte/data/__init__.py
flottekarte/data/geojson.py
flottekarte/extensions/__init__.py
flottekarte/extensions/boundary.py
flottekarte/extensions/cdll.py
flottekarte/extensions/gradients.py
flottekarte/extensions/grid.py
flottekarte/extensions/inverse.py
flottekarte/extensions/libflottekarte.so
flottekarte/extensions/meson.build
flottekarte/extensions/meson_options.txt
flottekarte/extensions/test-cdll.py
flottekarte/extensions/ticks.py
flottekarte/extensions/include/augmentedproj.hpp
flottekarte/extensions/include/boundary.hpp
flottekarte/extensions/include/gradient.hpp
flottekarte/extensions/include/grid.hpp
flottekarte/extensions/include/griddedinverter.hpp
flottekarte/extensions/include/invert.hpp
flottekarte/extensions/include/linalg.hpp
flottekarte/extensions/include/paths.hpp
flottekarte/extensions/include/pyapi.hpp
flottekarte/extensions/include/tickfinder.hpp
flottekarte/extensions/include/types.hpp
flottekarte/extensions/src/augmentedproj.cpp
flottekarte/extensions/src/boundary.cpp
flottekarte/extensions/src/gradient.cpp
flottekarte/extensions/src/grid.cpp
flottekarte/extensions/src/griddedinverter.cpp
flottekarte/extensions/src/invert.cpp
flottekarte/extensions/src/linalg.cpp
flottekarte/extensions/src/paths.cpp
flottekarte/extensions/src/pyapi.cpp
flottekarte/extensions/src/tickfinder.cpp
flottekarte/extensions/src/types.cpp
flottekarte/extensions/subprojects/libprojwrap.wrap
flottekarte-0.2.9.dist-info/COPYING
flottekarte-0.2.9.dist-info/LICENSE
flottekarte-0.2.9.dist-info/METADATA
flottekarte-0.2.9.dist-info/WHEEL
flottekarte-0.2.9.dist-info/top_level.txt
flottekarte-0.2.9.dist-info/RECORD
