Metadata-Version: 2.1
Name: flottekarte
Version: 0.2.9
Summary: Plotting with PROJ and Matplotlib.
Author-email: "Malte J. Ziebarth" <ziebarth@gfz-potsdam.de>
License: EUROPEAN UNION PUBLIC LICENCE v. 1.2
Project-URL: Homepage, https://github.com/mjziebarth/FlotteKarte
Project-URL: Bug Tracker, https://github.com/mjziebarth/FlotteKarte/issues
Project-URL: Documentation, https://mjziebarth.github.io/FlotteKarte/index.html
Classifier: Development Status :: 4 - Beta
Classifier: Framework :: Matplotlib
Classifier: Programming Language :: Python :: 3
Classifier: Programming Language :: C++
Classifier: License :: OSI Approved :: European Union Public Licence 1.2 (EUPL 1.2)
Classifier: Intended Audience :: Science/Research
Classifier: Topic :: Scientific/Engineering :: GIS
Classifier: Topic :: Scientific/Engineering :: Visualization
Classifier: Natural Language :: English
Classifier: Operating System :: POSIX :: Linux
Requires-Python: >=3.8
License-File: LICENSE
License-File: COPYING
